Metadata-Version: 1.0
Name: distributions2manu
Version: 0.1.2
Summary: Gaussian distributions
Home-page: UNKNOWN
Author: UNKNOWN
Author-email: UNKNOWN
License: UNKNOWN
Platform: UNKNOWN
